bluer_algo/__init__.py
bluer_algo/__main__.py
bluer_algo/config.env
bluer_algo/env.py
bluer_algo/functions.py
bluer_algo/host.py
bluer_algo/logger.py
bluer_algo/.abcli/abcli.sh
bluer_algo/.abcli/actions.sh
bluer_algo/.abcli/aka.sh
bluer_algo/.abcli/alias.sh
bluer_algo/.abcli/bluer_algo.sh
bluer_algo/.abcli/bps.sh
bluer_algo/.abcli/image_classifier.sh
bluer_algo/.abcli/socket.sh
bluer_algo/.abcli/tracker.sh
bluer_algo/.abcli/yolo.sh
bluer_algo/.abcli/bps/beacon.sh
bluer_algo/.abcli/bps/generate.sh
bluer_algo/.abcli/bps/install.sh
bluer_algo/.abcli/bps/introspect.sh
bluer_algo/.abcli/bps/loop.sh
bluer_algo/.abcli/bps/receiver.sh
bluer_algo/.abcli/bps/review.sh
bluer_algo/.abcli/bps/set_anchor.sh
bluer_algo/.abcli/bps/simulate.sh
bluer_algo/.abcli/bps/start_bluetooth.sh
bluer_algo/.abcli/bps/test.sh
bluer_algo/.abcli/bps/loop/start.sh
bluer_algo/.abcli/bps/loop/stop.sh
bluer_algo/.abcli/bps/simulate/timing.sh
bluer_algo/.abcli/image_classifier/dataset.sh
bluer_algo/.abcli/image_classifier/model.sh
bluer_algo/.abcli/image_classifier/dataset/ingest.sh
bluer_algo/.abcli/image_classifier/dataset/review.sh
bluer_algo/.abcli/image_classifier/dataset/sequence.sh
bluer_algo/.abcli/image_classifier/model/prediction_test.sh
bluer_algo/.abcli/image_classifier/model/train.sh
bluer_algo/.abcli/socket/test.sh
bluer_algo/.abcli/tests/README.sh
bluer_algo/.abcli/tests/bps_generate.sh
bluer_algo/.abcli/tests/bps_review.sh
bluer_algo/.abcli/tests/bps_simulate_timing.sh
bluer_algo/.abcli/tests/help.sh
bluer_algo/.abcli/tests/image_classifier_dataset_ingest.sh
bluer_algo/.abcli/tests/image_classifier_dataset_review.sh
bluer_algo/.abcli/tests/image_classifier_dataset_sequence.sh
bluer_algo/.abcli/tests/image_classifier_model_prediction_test.sh
bluer_algo/.abcli/tests/image_classifier_model_train.sh
bluer_algo/.abcli/tests/socket.sh
bluer_algo/.abcli/tests/tracker.sh
bluer_algo/.abcli/tests/tracker_list.sh
bluer_algo/.abcli/tests/tracker_sandbox.sh
bluer_algo/.abcli/tests/version.sh
bluer_algo-4.679.1.dist-info/licenses/LICENSE
bluer_algo-4.679.1.dist-info/METADATA
bluer_algo-4.679.1.dist-info/WHEEL
bluer_algo-4.679.1.dist-info/top_level.txt
bluer_algo-4.679.1.dist-info/RECORD
