Metadata-Version: 2.4
Name: bluer_algo
Version: 4.679.1
Summary: 🪄 AI Algo.
Home-page: https://github.com/kamangir/bluer-algo
Author: Arash Abadpour (Kamangir)
Author-email: arash.abadpour@gmail.com
License: CC0-1.0
Classifier: Programming Language :: Python :: 3
Classifier: Programming Language :: Unix Shell
Classifier: Operating System :: OS Independent
License-File: LICENSE
Requires-Dist: bluer_ai
Requires-Dist: kaggle
Requires-Dist: torch
Requires-Dist: torchvision
Requires-Dist: opencv-contrib-python
Requires-Dist: ultralytics
Dynamic: author
Dynamic: author-email
Dynamic: classifier
Dynamic: description
Dynamic: description-content-type
Dynamic: home-page
Dynamic: license
Dynamic: license-file
Dynamic: requires-dist
Dynamic: summary
